[
    {
        "id": 2,
        "state": true,
        "created_date": "2021-06-23",
        "modified_date": "2021-06-23",
        "deleted_date": "2021-06-23",
        "project_name": "Project Manage",
        "is_recurrent": false,
        "start_date": "2021-06-09",
        "end_date": "2021-07-02",
        "work_time": "00:00:10",
        "break_time": "00:00:01",
        "project_category": 1
    },
    {
        "id": 3,
        "state": true,
        "created_date": "2021-06-23",
        "modified_date": "2021-06-23",
        "deleted_date": "2021-06-23",
        "project_name": "Norma Juridica",
        "is_recurrent": false,
        "start_date": "2021-06-23",
        "end_date": "2021-06-30",
        "work_time": "00:00:10",
        "break_time": "00:00:01",
        "project_category": 2
    },
    {
        "id": 4,
        "state": true,
        "created_date": "2021-06-23",
        "modified_date": "2021-06-23",
        "deleted_date": "2021-06-23",
        "project_name": "Deporte",
        "is_recurrent": true,
        "start_date": "2021-06-23",
        "end_date": "2021-07-23",
        "work_time": "00:00:01",
        "break_time": "00:00:00",
        "project_category": 3
    }
]